djangocms_leaflet/__about__.py
djangocms_leaflet/__init__.py
djangocms_leaflet/apps.py
djangocms_leaflet/cms_plugins.py
djangocms_leaflet/models.py
djangocms_leaflet/locale/de/LC_MESSAGES/django.mo
djangocms_leaflet/locale/de/LC_MESSAGES/django.po
djangocms_leaflet/migrations/0001_initial.py
djangocms_leaflet/migrations/0002_auto_20200310_2328.py
djangocms_leaflet/migrations/0003_rename_name_map__name_remove_marker_name_and_more.py
djangocms_leaflet/migrations/0004_alter_map_set_marker.py
djangocms_leaflet/migrations/__init__.py
djangocms_leaflet/static/djangocms_leaflet/images/layers-2x.png
djangocms_leaflet/static/djangocms_leaflet/images/layers.png
djangocms_leaflet/static/djangocms_leaflet/images/marker-icon-2x.png
djangocms_leaflet/static/djangocms_leaflet/images/marker-icon.png
djangocms_leaflet/static/djangocms_leaflet/images/marker-shadow.png
djangocms_leaflet/static/djangocms_leaflet/images/leaflet-color-markers/marker-icon-2x-black.png
djangocms_leaflet/static/djangocms_leaflet/images/leaflet-color-markers/marker-icon-2x-blue.png
djangocms_leaflet/static/djangocms_leaflet/images/leaflet-color-markers/marker-icon-2x-gold.png
djangocms_leaflet/static/djangocms_leaflet/images/leaflet-color-markers/marker-icon-2x-green.png
djangocms_leaflet/static/djangocms_leaflet/images/leaflet-color-markers/marker-icon-2x-grey.png
djangocms_leaflet/static/djangocms_leaflet/images/leaflet-color-markers/marker-icon-2x-orange.png
djangocms_leaflet/static/djangocms_leaflet/images/leaflet-color-markers/marker-icon-2x-red.png
djangocms_leaflet/static/djangocms_leaflet/images/leaflet-color-markers/marker-icon-2x-violet.png
djangocms_leaflet/static/djangocms_leaflet/images/leaflet-color-markers/marker-icon-2x-yellow.png
djangocms_leaflet/static/djangocms_leaflet/images/leaflet-color-markers/marker-icon-black.png
djangocms_leaflet/static/djangocms_leaflet/images/leaflet-color-markers/marker-icon-blue.png
djangocms_leaflet-0.0.6.dist-info/METADATA
djangocms_leaflet-0.0.6.dist-info/WHEEL
djangocms_leaflet-0.0.6.dist-info/licenses/LICENSE.txt
djangocms_leaflet-0.0.6.dist-info/RECORD
