Metadata-Version: 2.4
Name: djangocms-leaflet
Version: 0.0.6
Summary: django CMS plug-ins for the JavaScript map library Leaflet
Project-URL: Documentation, https://github.com/MacLake/djangocms-leaflet#readme
Project-URL: Issues, https://github.com/MacLake/djangocms-leaflet/issues
Project-URL: Source, https://github.com/MacLake/djangocms-leaflet
Author-email: Jens-Erik Weber <Jens-Erik.Weber@passiv.de>
License-Expression: MIT
License-File: LICENSE.txt
Keywords: Leaflet,django CMS
Classifier: Development Status :: 4 - Beta
Classifier: Programming Language :: Python
Classifier: Programming Language :: Python :: 3.9
Classifier: Programming Language :: Python :: 3.10
Classifier: Programming Language :: Python :: 3.11
Classifier: Programming Language :: Python :: 3.12
Classifier: Programming Language :: Python :: Implementation :: CPython
Classifier: Programming Language :: Python :: Implementation :: PyPy
Requires-Python: >=3.9
Requires-Dist: django-cms>=3.11
Requires-Dist: django>=3.2
Requires-Dist: requests>=2.31
